rvenv/__init__.py
rvenv-0.2.data/scripts/rvenv
rvenv-0.2.dist-info/DESCRIPTION.rst
rvenv-0.2.dist-info/METADATA
rvenv-0.2.dist-info/metadata.json
rvenv-0.2.dist-info/RECORD
rvenv-0.2.dist-info/top_level.txt
rvenv-0.2.dist-info/WHEEL
