Metadata-Version: 2.0
Name: rvenv
Version: 0.2
Summary: Install and manage R packages in a python virtualenv
Home-page: https://github.com/nhoffman/rvenv
Author: Noah Hoffman
Author-email: noah.hoffman@gmail.com
License: MIT
Platform: UNKNOWN
Classifier: Development Status :: 3 - Alpha
Classifier: Environment :: Console
Classifier: Intended Audience :: Developers
Classifier: Intended Audience :: System Administrators
Classifier: Operating System :: POSIX
Classifier: Programming Language :: Python :: 2.7
